README.md
setup.py
lndconnect/__init__.py
lndconnect/uri.py
lndconnect.egg-info/PKG-INFO
lndconnect.egg-info/SOURCES.txt
lndconnect.egg-info/dependency_links.txt
lndconnect.egg-info/top_level.txt